rats/processors/__init__.py
rats/processors/_legacy_subpackages/__init__.py
rats/processors/_legacy_subpackages/_container.py
rats/processors/_legacy_subpackages/_interfaces.py
rats/processors/_legacy_subpackages/_typing.py
rats/processors/_legacy_subpackages/config/__init__.py
rats/processors/_legacy_subpackages/config/_app_plugin.py
rats/processors/_legacy_subpackages/config/_config_getters.py
rats/processors/_legacy_subpackages/config/_hydra_clients.py
rats/processors/_legacy_subpackages/config/_schemas.py
rats/processors/_legacy_subpackages/dag/__init__.py
rats/processors/_legacy_subpackages/dag/_app_plugin.py
rats/processors/_legacy_subpackages/dag/_client.py
rats/processors/_legacy_subpackages/dag/_dag.py
rats/processors/_legacy_subpackages/dag/_processor.py
rats/processors/_legacy_subpackages/dag/_utils.py
rats/processors/_legacy_subpackages/dag/_viz.py
rats/processors/_legacy_subpackages/example/__init__.py
rats/processors/_legacy_subpackages/example/__main__.py
rats/processors/_legacy_subpackages/example/_app_plugin.py
rats/processors/_legacy_subpackages/example/_pipeline.py
rats/processors/_legacy_subpackages/example/_processors.py
rats/processors/_legacy_subpackages/io/__init__.py
rats/processors/_legacy_subpackages/io/_app_plugin.py
rats/processors/_legacy_subpackages/io/_manifest.py
rats/processors/_legacy_subpackages/io/_plugin_register_rw.py
rats/processors/_legacy_subpackages/io/_register_rw.py
rats/processors/_legacy_subpackages/io/read_from_uri.py
rats/processors/_legacy_subpackages/io/type_rw_mappers.py
rats/processors/_legacy_subpackages/io/write_to_uri.py
rats/processors/_legacy_subpackages/ml/__init__.py
rats/processors/_legacy_subpackages/ml/_estimators.py
rats/processors/_legacy_subpackages/pipeline_operations/__init__.py
rats/processors/_legacy_subpackages/pipeline_operations/_app_plugin.py
rats/processors/_legacy_subpackages/pipeline_operations/_build_manifest_processor.py
rats_processors-0.1.3.dist-info/METADATA
rats_processors-0.1.3.dist-info/WHEEL
rats_processors-0.1.3.dist-info/entry_points.txt
rats_processors-0.1.3.dist-info/RECORD
