Metadata-Version: 2.1
Name: rats-processors
Version: 0.1.3
Summary: Rats Processors
Home-page: https://github.com/microsoft/rats/
License: MIT
Keywords: pipelines,machine learning,research
Requires-Python: >=3.10,<4.0
Classifier: License :: OSI Approved :: MIT License
Classifier: Programming Language :: Python :: 3
Classifier: Programming Language :: Python :: 3.10
Classifier: Programming Language :: Python :: 3.11
Classifier: Programming Language :: Python :: 3.12
Requires-Dist: dill (>=0.3.5,<0.4.0)
Requires-Dist: furl (>=2.1.3,<3.0.0)
Requires-Dist: hydra-core (>=1.3.2,<2.0.0)
Requires-Dist: hydra-zen
Requires-Dist: omegaconf
Requires-Dist: pydot (>=1.4.2,<3.0.0)
Requires-Dist: rats-apps (>=0.1.3,<0.2.0)
Requires-Dist: rats-pipelines (>=0.1.3,<0.2.0)
Project-URL: Documentation, https://microsoft.github.io/rats/
Project-URL: Repository, https://github.com/microsoft/rats/
